tests/fixtures/__init__.py
tests/fixtures/model_preds_fixtures.py
tonks/__init__.py
tonks/_version.py
tonks/config.py
tonks/dataloader.py
tonks/exc.py
tonks/learner.py
tonks/ensemble/__init__.py
tonks/ensemble/dataset.py
tonks/ensemble/models/__init__.py
tonks/ensemble/models/multi_task_ensemble.py
tonks/text/__init__.py
tonks/text/dataset.py
tonks/text/models/__init__.py
tonks/text/models/multi_task_bert.py
tonks/vision/__init__.py
tonks/vision/config.py
tonks/vision/dataset.py
tonks/vision/helpers.py
tonks/vision/models/__init__.py
tonks/vision/models/multi_task_resnet.py
tonks-1.0.0.data/data/LICENSE.txt
tonks-1.0.0.dist-info/LICENSE.txt
tonks-1.0.0.dist-info/METADATA
tonks-1.0.0.dist-info/WHEEL
tonks-1.0.0.dist-info/top_level.txt
tonks-1.0.0.dist-info/RECORD
