Metadata-Version: 2.1
Name: tonks
Version: 1.0.0
Summary: General purpose multi-task classification library
Home-page: https://github.com/shoprunner/tonks
Author: Nicole Carlson, Michael Sugimura
License: BSD-3-Clause
Platform: UNKNOWN
Requires-Dist: creevey
Requires-Dist: fastprogress
Requires-Dist: joblib
Requires-Dist: numpy
Requires-Dist: Pillow (<7.0.0)
Requires-Dist: transformers (>=2.3.0)
Requires-Dist: sentencepiece (!=0.1.92)
Requires-Dist: scikit-learn
Requires-Dist: torch (==1.2.0)
Requires-Dist: torchvision (==0.2.1)
